prl/__init__.py
prl/cli/__init__.py
prl/cli/auth.py
prl/cli/main.py
prl/cli/rag.py
prl/cli/run.py
prl/cli/suite.py
prl/cli/util.py
prl/sdk/__init__.py
prl/sdk/auth.py
prl/sdk/exceptions.py
prl/sdk/run.py
prl/sdk/sdk.py
prl/sdk/suite.py
prl/sdk/util.py
prl/sdk/jsonschemas/run_params_schema.json
prl/sdk/jsonschemas/suiteschema.json
prl_cli-0.0.31.dist-info/METADATA
prl_cli-0.0.31.dist-info/WHEEL
prl_cli-0.0.31.dist-info/entry_points.txt
prl_cli-0.0.31.dist-info/top_level.txt
prl_cli-0.0.31.dist-info/RECORD
