Metadata-Version: 2.1
Name: prl-cli
Version: 0.0.31
Home-page: http://pypi.python.org/pypi/prl-cli/
Author: Langston Nashold, Rayan Krishnan
Requires-Dist: Click
Requires-Dist: gql
Requires-Dist: attrs
Requires-Dist: jsonschema
Requires-Dist: tqdm
Requires-Dist: boto3
Requires-Dist: requests
Requires-Dist: aiohttp
Requires-Dist: pandas
Requires-Dist: requests-toolbelt
